{
    "id": 7,
    "productId": "cabinateSideboard7",
    "title": " Carleson Sheesham Wood Sideboard In Scratch Resistant Warm Chestnut Finish",
    "brand": "Amberville from Pepperfry",
    "price": {
        "sell": "30,499",
        "mrp": "40,999"
    },
    "discount": {
        "price": "10,500 ",
        "percent": "(26% off)"
    },
    "rating": "4.5",
    "image": "https://ii1.pepperfry.com/media/catalog/product/c/a/494x544/carleson-sheesham-wood-sideboard-in-warm-chestnut-finish-carleson-sheesham-wood-sideboard-in-warm-ch-mb505q.jpg",
    "category": "cabinate and sideboard",
    "extraoffer": "Earn 763 Extra Pepperfry Credits (Worth ₹763)",
    "shipping": ""
}