{
    "id": 26,
    "productId": "centreTable26",
    "title": "Bonita Metal Coffee Table In White Colour With Marble Top",
    "brand": "Casacraft from Pepperfry",
    "price": {
        "sell": "16,499",
        "mrp": "20,999"
    },
    "discount": {
        "price": "₹4,500 ",
        "percent": "(21% off)"
    },
    "rating": "4.5",
    "image": "https://ii1.pepperfry.com/media/catalog/product/b/o/494x544/bonita-metal-coffee-table-in-white-colour-with-marble-top-bonita-metal-coffee-table-in-white-colour--z2xygt.jpg",
    "category": "centreTable",
    "extraoffer": "Earn 413 Extra Pepperfry Credits (Worth ₹413)",
    "shipping": "Express Shipping in 2 days"
}