{
    "id": 18,
    "productId": "studyTable18",
    "title": " Antonio Solid Wood Writing Table In Distress Finish",
    "brand": "Bohemiana from Pepperfry",
    "price": {
        "sell": "16,999 ",
        "mrp": "21,999"
    },
    "discount": {
        "price": "5,000",
        "percent": " (23% off)"
    },
    "rating": "4.5",
    "image": "https://ii1.pepperfry.com/media/catalog/product/a/n/494x544/antonio-solid-wood-study-table-in-distress-finish-by-bohemiana-antonio-solid-wood-study-table-in-dis-svc1iu.jpg",
    "category": "studyTable",
    "extraoffer": "Earn 425 Extra Pepperfry Credits (Worth ₹425)",
    "shipping": ""
}